MANIFEST.in
README.txt
setup.py
XStatic_Leaflet.egg-info/PKG-INFO
XStatic_Leaflet.egg-info/SOURCES.txt
XStatic_Leaflet.egg-info/dependency_links.txt
XStatic_Leaflet.egg-info/namespace_packages.txt
XStatic_Leaflet.egg-info/not-zip-safe
XStatic_Leaflet.egg-info/top_level.txt
xstatic/__init__.py
xstatic/pkg/__init__.py
xstatic/pkg/leaflet/__init__.py
xstatic/pkg/leaflet/__pycache__/__init__.cpython-311.pyc
xstatic/pkg/leaflet/data/leaflet-src.esm.js
xstatic/pkg/leaflet/data/leaflet-src.esm.js.map
xstatic/pkg/leaflet/data/leaflet-src.js
xstatic/pkg/leaflet/data/leaflet-src.js.map
xstatic/pkg/leaflet/data/leaflet-src.map
xstatic/pkg/leaflet/data/leaflet.css
xstatic/pkg/leaflet/data/leaflet.js
xstatic/pkg/leaflet/data/leaflet.js.map
xstatic/pkg/leaflet/data/images/layers-2x.png
xstatic/pkg/leaflet/data/images/layers.png
xstatic/pkg/leaflet/data/images/marker-icon-2x.png
xstatic/pkg/leaflet/data/images/marker-icon.png
xstatic/pkg/leaflet/data/images/marker-shadow.png