Metadata-Version: 2.1
Name: XStatic-Leaflet
Version: 1.9.3.0
Summary: Leaflet 1.9.3 (XStatic packaging standard)
Home-page: https://leafletjs.com/
Maintainer: Benjamin Dauvergne
Maintainer-email: bdauvergne@entrouvert.com
License: (same as Leaflet)
Keywords: leaflet xstatic
Platform: any
